radar/__init__.py
radar/measurement.py
radar/radar.py
radar/visualize.py
radar_assignment-0.2.0.dist-info/METADATA
radar_assignment-0.2.0.dist-info/WHEEL
radar_assignment-0.2.0.dist-info/top_level.txt
radar_assignment-0.2.0.dist-info/RECORD
