Metadata-Version: 2.4
Name: radar-assignment
Version: 0.2.0
Summary: Helper packages for a
Requires-Python: >=3.13
Requires-Dist: notebook>=7.4.3
Requires-Dist: anywidget>=0.9.18
Requires-Dist: ipywidgets>=8.1.7
Requires-Dist: plotly>=6.1.2
Requires-Dist: pyserial>=3.5
Requires-Dist: asyncio>=3.4.3
Requires-Dist: dash>=3.0.4
